perun/proxygui/__init__.py
perun/proxygui/app.py
perun/proxygui/jwt.py
perun/proxygui/logout_manager.py
perun/proxygui/oauth.py
perun/proxygui/user_manager.py
perun/proxygui/api/__init__.py
perun/proxygui/api/backchannel_logout_api.py
perun/proxygui/api/ban_api.py
perun/proxygui/api/consent_api.py
perun/proxygui/api/heuristic_api.py
perun/proxygui/gui/__init__.py
perun/proxygui/gui/gui.py
perun/proxygui/gui/static/campus-idp-muni.js
perun/proxygui/gui/static/campus-idp.css
perun/proxygui/gui/static/campus-idp.js
perun/proxygui/gui/static/jquery-3.6.0.min.js
perun/proxygui/gui/static/proxygui.css
perun/proxygui/gui/static/proxygui.js
perun/proxygui/gui/static/MuniWeb/_ins/css/_atoms.scss
perun/proxygui/gui/static/MuniWeb/_ins/css/_molecules.scss
perun/proxygui/gui/static/MuniWeb/_ins/css/_organisms.scss
perun/proxygui/gui/static/MuniWeb/_ins/css/style.css
perun/proxygui/gui/static/MuniWeb/_ins/css/style.scss
perun/proxygui/gui/static/MuniWeb/_ins/css/.map/style.css.map
perun/proxygui/gui/static/MuniWeb/_ins/css/atoms/_avatar.scss
perun/proxygui/gui/static/MuniWeb/_ins/css/atoms/_calendar.scss
perun/proxygui/gui/static/MuniWeb/_ins/css/atoms/_dropdown.scss
perun/proxygui/gui/static/MuniWeb/_ins/css/atoms/_modal.scss
perun/proxygui/gui/static/MuniWeb/_ins/css/lib/_icons.scss
perun/proxygui/gui/static/MuniWeb/_ins/css/molecules/box/_article.scss
perun/proxygui/gui/static/MuniWeb/_ins/css/molecules/box/_calendar.scss
perun/proxygui/gui/static/MuniWeb/_ins/css/molecules/box/_chat-message.scss
perun/proxygui/gui/static/MuniWeb/_ins/css/molecules/box/_dashboard-header.scss
perun/proxygui/gui/static/MuniWeb/_ins/css/molecules/box/_documents.scss
perun/proxygui/gui/static/MuniWeb/_ins/css/molecules/box/_food-menu.scss
perun/proxygui/gui/static/MuniWeb/_ins/css/molecules/box/_images.scss
perun/proxygui/gui/static/MuniWeb/_ins/css/molecules/box/_notifications.scss
perun/proxygui/gui/static/MuniWeb/_ins/css/molecules/box/_settings.scss
perun.proxygui-8.2.2.dist-info/LICENSE
perun.proxygui-8.2.2.dist-info/METADATA
perun.proxygui-8.2.2.dist-info/WHEEL
perun.proxygui-8.2.2.dist-info/top_level.txt
perun.proxygui-8.2.2.dist-info/RECORD
