Metadata-Version: 2.1
Name: perun.proxygui
Version: 8.2.2
Summary: Module with GUI and API for Perun ProxyIdP
Home-page: https://gitlab.ics.muni.cz/perun/perun-proxyidp/proxyidp-gui.git
Requires-Python: >=3.9
License-File: LICENSE
Requires-Dist: Authlib==1.3.0
Requires-Dist: setuptools
Requires-Dist: PyYAML==6.0.1
Requires-Dist: Flask==2.3.3
Requires-Dist: Flask-pyoidc==3.14.3
Requires-Dist: Flask-Babel==3.1.0
Requires-Dist: perun.connector==3.8.1
Requires-Dist: python-smail==0.9.0
Requires-Dist: SQLAlchemy==2.0.29
Requires-Dist: pymongo~=4.6
Requires-Dist: validators==0.28.1
Requires-Dist: idpyoidc==2.1.0
Requires-Dist: python-dateutil==2.9.0
Requires-Dist: Jinja2==3.1.3
Requires-Dist: requests==2.31.0
Requires-Dist: Flask-Session[mongodb]~=0.8
Requires-Dist: pysaml2==7.4.2
Requires-Dist: cryptojwt==1.8.3
Requires-Dist: user-agents==2.2.0
Requires-Dist: flask-smorest==0.42.3
Requires-Dist: marshmallow==3.21.1
Requires-Dist: deepdiff==6.7.1
Provides-Extra: postgresql
Requires-Dist: psycopg2-binary==2.9.9; extra == "postgresql"
Requires-Dist: Flask-session[sqlalchemy]~=0.8; extra == "postgresql"
